warp_agent_sdk/__init__.py
warp_agent_sdk/_base_client.py
warp_agent_sdk/_client.py
warp_agent_sdk/_compat.py
warp_agent_sdk/_constants.py
warp_agent_sdk/_exceptions.py
warp_agent_sdk/_files.py
warp_agent_sdk/_models.py
warp_agent_sdk/_qs.py
warp_agent_sdk/_resource.py
warp_agent_sdk/_response.py
warp_agent_sdk/_streaming.py
warp_agent_sdk/_types.py
warp_agent_sdk/_version.py
warp_agent_sdk/py.typed
warp_agent_sdk/_utils/__init__.py
warp_agent_sdk/_utils/_compat.py
warp_agent_sdk/_utils/_datetime_parse.py
warp_agent_sdk/_utils/_logs.py
warp_agent_sdk/_utils/_proxy.py
warp_agent_sdk/_utils/_reflection.py
warp_agent_sdk/_utils/_resources_proxy.py
warp_agent_sdk/_utils/_streams.py
warp_agent_sdk/_utils/_sync.py
warp_agent_sdk/_utils/_transform.py
warp_agent_sdk/_utils/_typing.py
warp_agent_sdk/_utils/_utils.py
warp_agent_sdk/lib/.keep
warp_agent_sdk/resources/__init__.py
warp_agent_sdk/resources/agent/__init__.py
warp_agent_sdk/resources/agent/agent.py
warp_agent_sdk/resources/agent/tasks.py
warp_agent_sdk/types/__init__.py
warp_agent_sdk/types/agent_run_params.py
warp_agent_sdk/types/agent_run_response.py
warp_agent_sdk/types/ambient_agent_config.py
warp_agent_sdk/types/ambient_agent_config_param.py
warp_agent_sdk/types/agent/__init__.py
warp_agent_sdk/types/agent/task_item.py
warp_agent_sdk/types/agent/task_list_params.py
warp_agent_sdk/types/agent/task_list_response.py
warp_agent_sdk/types/agent/task_source_type.py
warp_agent_sdk/types/agent/task_state.py
warp_agent_sdk-0.3.0.dist-info/METADATA
warp_agent_sdk-0.3.0.dist-info/WHEEL
warp_agent_sdk-0.3.0.dist-info/licenses/LICENSE
warp_agent_sdk-0.3.0.dist-info/RECORD
